heinanalyticalcontrol/__init__.py
heinanalyticalcontrol/analysis/__init__.py
heinanalyticalcontrol/analysis/base_spectrum.py
heinanalyticalcontrol/analysis/spec_utils.py
heinanalyticalcontrol/analysis/utils.py
heinanalyticalcontrol/devices/__init__.py
heinanalyticalcontrol/devices/Agilent/__init__.py
heinanalyticalcontrol/devices/Agilent/chemstation.py
heinanalyticalcontrol/devices/Agilent/chromatogram.py
heinanalyticalcontrol/devices/Agilent/hplc.py
heinanalyticalcontrol/devices/Agilent/hplc_param_types.py
heinanalyticalcontrol/devices/Magritek/__init__.py
heinanalyticalcontrol/devices/Magritek/Spinsolve/__init__.py
heinanalyticalcontrol/devices/Magritek/Spinsolve/commands.py
heinanalyticalcontrol/devices/Magritek/Spinsolve/spectrum.py
heinanalyticalcontrol/devices/Magritek/Spinsolve/spinsolve.py
heinanalyticalcontrol/devices/Magritek/Spinsolve/utils/__init__.py
heinanalyticalcontrol/devices/Magritek/Spinsolve/utils/connection.py
heinanalyticalcontrol/devices/Magritek/Spinsolve/utils/constants.py
heinanalyticalcontrol/devices/Magritek/Spinsolve/utils/exceptions.py
heinanalyticalcontrol/devices/Magritek/Spinsolve/utils/parser.py
heinanalyticalcontrol/devices/Magritek/Spinsolve/utils/shimming.py
heinanalyticalcontrol/devices/Magritek/Spinsolve/utils/spinsolve_logging.py
heinanalyticalcontrol/devices/OceanOptics/__init__.py
heinanalyticalcontrol/devices/OceanOptics/oceanoptics.py
heinanalyticalcontrol/devices/OceanOptics/IR/NIRQuest512.py
heinanalyticalcontrol/devices/OceanOptics/IR/__init__.py
heinanalyticalcontrol/devices/OceanOptics/IR/ir_spectrum.py
heinanalyticalcontrol/devices/OceanOptics/Raman/__init__.py
heinanalyticalcontrol/devices/OceanOptics/Raman/raman_control.py
heinanalyticalcontrol/devices/OceanOptics/Raman/raman_spectrum.py
heinanalyticalcontrol/devices/OceanOptics/UV/QEPro2192.py
heinanalyticalcontrol/devices/OceanOptics/UV/__init__.py
heinanalyticalcontrol/devices/OceanOptics/UV/uv_spectrum.py
hein_analytical_control-0.4.6.dist-info/LICENSE
hein_analytical_control-0.4.6.dist-info/METADATA
hein_analytical_control-0.4.6.dist-info/WHEEL
hein_analytical_control-0.4.6.dist-info/top_level.txt
hein_analytical_control-0.4.6.dist-info/RECORD
