Metadata-Version: 2.1
Name: hein-analytical-control
Version: 0.4.6
Summary: Library to interact with Chemstation software, primarily used in Hein lab
Home-page: https://gitlab.com/heingroup/hein-analytical-control
Author: Lucy Hao
Author-email: lhao03@student.ubc.ca
Classifier: Programming Language :: Python :: 3
Classifier: License :: OSI Approved :: MIT License
Classifier: Operating System :: OS Independent
License-File: LICENSE
Requires-Dist: nmrglue
Requires-Dist: polling
Requires-Dist: seabreeze
